<?xml version="1.0" encoding="UTF-8"?><workflow uri="http://www.myexperiment.org/workflow.xml?id=1103" resource="http://www.myexperiment.org/workflows/1103" id="1103" version="6">  <id>1103</id>  <title>OpenTox Get Algorithms on TUM server</title>  <description>Get URIs of all available algorithms on TUM server</description>  <type resource="http://www.myexperiment.org/content_types/2" uri="http://www.myexperiment.org/type.xml?id=2" id="2">Taverna 2</type>  <uploader resource="http://www.myexperiment.org/users/6658" uri="http://www.myexperiment.org/user.xml?id=6658" id="6658">Wicker</uploader>  <created-at>2011-05-11 14:33:42 UTC</created-at>  <preview>http://www.myexperiment.org/workflows/1103/versions/6/previews/full</preview>  <svg>http://www.myexperiment.org/workflows/1103/versions/6/previews/svg</svg>  <license-type resource="http://www.myexperiment.org/licenses/1" uri="http://www.myexperiment.org/license.xml?id=1" id="1">by-nd</license-type>  <content-uri>https://myexperiment.org/workflows/1103/download/OpenTox_Get_Algorithms_on_TUM_server-v.t2flow</content-uri>  <content-type>application/vnd.taverna.t2flow+xml</content-type>  <tags>    <tag uri="http://www.myexperiment.org/tag.xml?id=1738" resource="http://www.myexperiment.org/tags/1738" id="1738">opentox</tag>  </tags></workflow>