<?xml version="1.0" encoding="UTF-8"?><workflow uri="http://www.myexperiment.org/workflow.xml?id=1577" resource="http://www.myexperiment.org/workflows/1577" id="1577" version="1">  <id>1577</id>  <title>Is Parameter Optimization Useful</title>  <description>&lt;p&gt;This process compares two 10x10fold cross-validations with linear SVM for classification. One use the heuristic parameter choice C=1/avg(K(x,x)) and the other uses an internal 5fold cross-validation to tune the parameter C. Afterwards both performance values are compared via ANOVA and T-test to check whether there is a significant difference between both performance values.&lt;/p&gt;&#13;&lt;p&gt;The behaviour of the optimized 10x10 XV is similar to that of the experiment &lt;a href="http://www.myexperiment.org/workflows/1576"&gt;10x10fold_XV_with_optimizedSVM_classification&lt;/a&gt;.&lt;/p&gt;&#13;&lt;p&gt;&amp;nbsp;&lt;/p&gt;</description>  <type resource="http://www.myexperiment.org/content_types/62" uri="http://www.myexperiment.org/type.xml?id=62" id="62">RapidMiner</type>  <uploader resource="http://www.myexperiment.org/users/12000" uri="http://www.myexperiment.org/user.xml?id=12000" id="12000">Benschowe</uploader>  <created-at>2010-10-28 09:08:07 UTC</created-at>  <preview>http://www.myexperiment.org/workflows/1577/versions/1/previews/full</preview>  <svg>http://www.myexperiment.org/workflows/1577/versions/1/previews/svg</svg>  <license-type resource="http://www.myexperiment.org/licenses/1" uri="http://www.myexperiment.org/license.xml?id=1" id="1">by-nd</license-type>  <content-uri>https://myexperiment.org/workflows/1577/download/Is_Parameter_Optimization_Useful-v.txt</content-uri>  <content-type>application/vnd.rapidminer.rmp+zip</content-type>  <tags/></workflow>