<?xml version="1.0" encoding="UTF-8"?><workflow uri="http://www.myexperiment.org/workflow.xml?id=1623" resource="http://www.myexperiment.org/workflows/1623" id="1623" version="1">  <id>1623</id>  <title>Byte Array to string - non empty value</title>  <description>&lt;p&gt;The beanshell converts the string 'hello' to a byte array which is then converted back to the string 'hello' by the Byte_Array_to_string service.&lt;/p&gt;</description>  <type resource="http://www.myexperiment.org/content_types/2" uri="http://www.myexperiment.org/type.xml?id=2" id="2">Taverna 2</type>  <uploader resource="http://www.myexperiment.org/users/30" uri="http://www.myexperiment.org/user.xml?id=30" id="30">Alan Williams</uploader>  <created-at>2010-10-29 13:26:10 UTC</created-at>  <preview>http://www.myexperiment.org/workflows/1623/versions/1/previews/full</preview>  <svg>http://www.myexperiment.org/workflows/1623/versions/1/previews/svg</svg>  <license-type resource="http://www.myexperiment.org/licenses/3" uri="http://www.myexperiment.org/license.xml?id=3" id="3">by</license-type>  <content-uri>https://myexperiment.org/workflows/1623/download/Byte_Array_to_string_-_non_empty_value-v.t2flow</content-uri>  <content-type>application/vnd.taverna.t2flow+xml</content-type>  <tags/></workflow>