<?xml version="1.0" encoding="UTF-8"?><workflow uri="http://www.myexperiment.org/workflow.xml?id=2421" resource="http://www.myexperiment.org/workflows/2421" id="2421" version="1">  <id>2421</id>  <title>Get Silly Vamp</title>  <description>&lt;div&gt;This workflow grabs the Silly Vamp comic strip. It is inspired by the Taverna workflow to get the latest XKCD comic.&lt;/div&gt;&#13;&lt;div&gt;&amp;nbsp;&lt;/div&gt;&#13;&lt;div&gt;The comic date can be customized. Please right-click on &amp;quot;IMAGE NAME&amp;quot; and change the value&lt;/div&gt;&#13;&lt;div&gt;to the specific date you want. The date format is&lt;/div&gt;&#13;&lt;div&gt;&amp;nbsp;&lt;/div&gt;&#13;&lt;div&gt;YYMMDD&lt;/div&gt;&#13;&lt;div&gt;&amp;nbsp;&lt;/div&gt;&#13;&lt;div&gt;For example, June 26, 2011 would be:&lt;/div&gt;&#13;&lt;div&gt;&amp;nbsp;&lt;/div&gt;&#13;&lt;div&gt;110626&lt;/div&gt;</description>  <type resource="http://www.myexperiment.org/content_types/14" uri="http://www.myexperiment.org/type.xml?id=14" id="14">Kepler</type>  <uploader resource="http://www.myexperiment.org/users/18934" uri="http://www.myexperiment.org/user.xml?id=18934" id="18934">Kayleigh Ayn Bohémier</uploader>  <created-at>2011-09-27 18:17:58 UTC</created-at>  <preview>http://www.myexperiment.org/workflows/2421/versions/1/previews/full</preview>  <svg>http://www.myexperiment.org/workflows/2421/versions/1/previews/svg</svg>  <license-type resource="http://www.myexperiment.org/licenses/2" uri="http://www.myexperiment.org/license.xml?id=2" id="2">by-sa</license-type>  <content-uri>https://myexperiment.org/workflows/2421/download/Get_Silly_Vamp-v.kar</content-uri>  <content-type>application/octet-stream</content-type>  <tags>    <tag uri="http://www.myexperiment.org/tag.xml?id=2996" resource="http://www.myexperiment.org/tags/2996" id="2996">ist600</tag>    <tag uri="http://www.myexperiment.org/tag.xml?id=1241" resource="http://www.myexperiment.org/tags/1241" id="1241">kepler</tag>    <tag uri="http://www.myexperiment.org/tag.xml?id=83" resource="http://www.myexperiment.org/tags/83" id="83">comic</tag>  </tags></workflow>