<?xml version="1.0" encoding="UTF-8"?><workflow uri="http://www.myexperiment.org/workflow.xml?id=3183" resource="http://www.myexperiment.org/workflows/3183" id="3183" version="1">  <id>3183</id>  <title>Merkel Government Statement Analysis</title>  <description>&lt;p&gt;Calculates the 100 most important words of each governmental statement from chancellor Merkel based their log likelihood values (compared to all govermental statements from her). Check out the pack -&amp;nbsp;http://www.myexperiment.org/packs/333.html to get the workflow with required text data.&lt;/p&gt;</description>  <type resource="http://www.myexperiment.org/content_types/96" uri="http://www.myexperiment.org/type.xml?id=96" id="96">Tesla</type>  <uploader resource="http://www.myexperiment.org/users/20861" uri="http://www.myexperiment.org/user.xml?id=20861" id="20861">jhermes</uploader>  <created-at>2012-09-19 14:48:21 UTC</created-at>  <preview>http://www.myexperiment.org/workflows/3183/versions/1/previews/full</preview>  <svg>http://www.myexperiment.org/workflows/3183/versions/1/previews/svg</svg>  <license-type resource="http://www.myexperiment.org/licenses/2" uri="http://www.myexperiment.org/license.xml?id=2" id="2">by-sa</license-type>  <content-uri>https://myexperiment.org/workflows/3183/download/Merkel_Government_Statement_Analysis-v.graph</content-uri>  <content-type>application/octet-stream</content-type>  <tags>    <tag uri="http://www.myexperiment.org/tag.xml?id=3642" resource="http://www.myexperiment.org/tags/3642" id="3642">log likelihood</tag>  </tags></workflow>