<?xml version="1.0" encoding="UTF-8"?><workflow uri="http://www.myexperiment.org/workflow.xml?id=3699" resource="http://www.myexperiment.org/workflows/3699" id="3699" version="1">  <id>3699</id>  <title>Generate Spectral Library </title>  <description>This work is licensed under a Creative Commons Attribution-ShareAlike 3.0 Unported License (CC BY-SA). Copyright© 2012 Yassene MohammedPlease send your feedback, questions, comments and suggestions for improvement to y.mohammed@lumc.nl14 November 2012Yassene</description>  <type resource="http://www.myexperiment.org/content_types/2" uri="http://www.myexperiment.org/type.xml?id=2" id="2">Taverna 2</type>  <uploader resource="http://www.myexperiment.org/users/17146" uri="http://www.myexperiment.org/user.xml?id=17146" id="17146">Yassene</uploader>  <created-at>2013-08-16 13:47:47 UTC</created-at>  <preview>http://www.myexperiment.org/workflows/3699/versions/1/previews/full</preview>  <svg>http://www.myexperiment.org/workflows/3699/versions/1/previews/svg</svg>  <license-type resource="http://www.myexperiment.org/licenses/2" uri="http://www.myexperiment.org/license.xml?id=2" id="2">by-sa</license-type>  <content-uri>https://myexperiment.org/workflows/3699/download/Generate_Spectral_Library_-v.t2flow</content-uri>  <content-type>application/vnd.taverna.t2flow+xml</content-type>  <tags>    <tag uri="http://www.myexperiment.org/tag.xml?id=405" resource="http://www.myexperiment.org/tags/405" id="405">proteomics</tag>    <tag uri="http://www.myexperiment.org/tag.xml?id=3866" resource="http://www.myexperiment.org/tags/3866" id="3866">spectral library</tag>    <tag uri="http://www.myexperiment.org/tag.xml?id=298" resource="http://www.myexperiment.org/tags/298" id="298">mass spectrometry</tag>  </tags></workflow>