<?xml version="1.0" encoding="UTF-8"?><workflow uri="http://www.myexperiment.org/workflow.xml?id=5042" resource="http://www.myexperiment.org/workflows/5042" id="5042" version="1">  <id>5042</id>  <title>Tratamento de erro para WSDL</title>  <description>&lt;p&gt;Verifica se web service est&amp;aacute; ativo antes de propriamente execut&amp;aacute;-lo, como forma de tratamento de erro, enviando mensagem de alerta caso erro ocorra.&lt;/p&gt;</description>  <type resource="http://www.myexperiment.org/content_types/2" uri="http://www.myexperiment.org/type.xml?id=2" id="2">Taverna 2</type>  <uploader resource="http://www.myexperiment.org/users/65675" uri="http://www.myexperiment.org/user.xml?id=65675" id="65675">Johnathan Melo Neto</uploader>  <created-at>2017-10-30 20:37:20 UTC</created-at>  <preview>http://www.myexperiment.org/workflows/5042/versions/1/previews/full</preview>  <svg>http://www.myexperiment.org/workflows/5042/versions/1/previews/svg</svg>  <license-type resource="http://www.myexperiment.org/licenses/2" uri="http://www.myexperiment.org/license.xml?id=2" id="2">by-sa</license-type>  <content-uri>https://myexperiment.org/workflows/5042/download/Tratamento_de_erro_para_WSDL-v.t2flow</content-uri>  <content-type>application/vnd.taverna.t2flow+xml</content-type>  <tags/></workflow>