<?xml version="1.0" encoding="UTF-8"?><workflow uri="http://www.myexperiment.org/workflow.xml?id=604" resource="http://www.myexperiment.org/workflows/604" id="604" version="2">  <id>604</id>  <title>TextGrid: Test workflow</title>  <description>&lt;p&gt;This is a first test workflow that demonstrate, how to use the GWES for a document-style Web Service within TextGrid.&lt;/p&gt;</description>  <type resource="http://www.myexperiment.org/content_types/7" uri="http://www.myexperiment.org/type.xml?id=7" id="7">GWorkflowDL</type>  <uploader resource="http://www.myexperiment.org/users/1333" uri="http://www.myexperiment.org/user.xml?id=1333" id="1333">Andreas Hoheisel</uploader>  <created-at>2008-12-17 09:54:59 UTC</created-at>  <preview>http://www.myexperiment.org/workflows/604/versions/2/previews/full</preview>  <svg>http://www.myexperiment.org/workflows/604/versions/2/previews/svg</svg>  <license-type resource="http://www.myexperiment.org/licenses/2" uri="http://www.myexperiment.org/license.xml?id=2" id="2">by-sa</license-type>  <content-uri>https://myexperiment.org/workflows/604/download/TextGrid__Test_workflow-v.gwdl</content-uri>  <content-type>application/octet-stream</content-type>  <tags>    <tag uri="http://www.myexperiment.org/tag.xml?id=1044" resource="http://www.myexperiment.org/tags/1044" id="1044">d-grid</tag>    <tag uri="http://www.myexperiment.org/tag.xml?id=555" resource="http://www.myexperiment.org/tags/555" id="555">example</tag>    <tag uri="http://www.myexperiment.org/tag.xml?id=1045" resource="http://www.myexperiment.org/tags/1045" id="1045">gwes</tag>    <tag uri="http://www.myexperiment.org/tag.xml?id=1042" resource="http://www.myexperiment.org/tags/1042" id="1042">gworkflowdl</tag>    <tag uri="http://www.myexperiment.org/tag.xml?id=1077" resource="http://www.myexperiment.org/tags/1077" id="1077">textgrid</tag>  </tags></workflow>